odoo8_addon_product_supplierinfo_for_customer_sale-8.0.1.0.0-py2.7-nspkg.pth
odoo8_addon_product_supplierinfo_for_customer_sale-8.0.1.0.0.dist-info/DESCRIPTION.rst
odoo8_addon_product_supplierinfo_for_customer_sale-8.0.1.0.0.dist-info/METADATA
odoo8_addon_product_supplierinfo_for_customer_sale-8.0.1.0.0.dist-info/RECORD
odoo8_addon_product_supplierinfo_for_customer_sale-8.0.1.0.0.dist-info/WHEEL
odoo8_addon_product_supplierinfo_for_customer_sale-8.0.1.0.0.dist-info/metadata.json
odoo8_addon_product_supplierinfo_for_customer_sale-8.0.1.0.0.dist-info/namespace_packages.txt
odoo8_addon_product_supplierinfo_for_customer_sale-8.0.1.0.0.dist-info/top_level.txt
odoo_addons/product_supplierinfo_for_customer_sale/README.rst
odoo_addons/product_supplierinfo_for_customer_sale/__init__.py
odoo_addons/product_supplierinfo_for_customer_sale/__openerp__.py
odoo_addons/product_supplierinfo_for_customer_sale/models/__init__.py
odoo_addons/product_supplierinfo_for_customer_sale/models/product_product.py
odoo_addons/product_supplierinfo_for_customer_sale/static/description/configuration_customer.png
odoo_addons/product_supplierinfo_for_customer_sale/static/description/description_code.png
odoo_addons/product_supplierinfo_for_customer_sale/static/description/description_code_2.png
odoo_addons/product_supplierinfo_for_customer_sale/static/description/search_code.png
odoo_addons/product_supplierinfo_for_customer_sale/static/description/search_code_2.png
odoo_addons/product_supplierinfo_for_customer_sale/tests/__init__.py
odoo_addons/product_supplierinfo_for_customer_sale/tests/test_product_name_search.py
odoo_addons/product_supplierinfo_for_customer_sale/views/sale_view.xml
