Metadata-Version: 2.0
Name: odoo8-addon-product-supplierinfo-for-customer-sale
Version: 8.0.1.0.0
Summary: Product supplier info for customer - sale
Home-page: http://www.vauxoo.com/
Author: Vauxoo, Odoo Community Association (OCA)
Author-email: support@odoo-community.org
License: AGPL-3
Platform: UNKNOWN
Classifier: Programming Language :: Python :: 2.7
Classifier: Framework :: Odoo
Classifier: License :: OSI Approved :: GNU Affero General Public License v3
Requires-Dist: odoo (<9.0a,>=8.0a)
Requires-Dist: odoo8-addon-product-supplierinfo-for-customer
